{
  "system": {
    "gin_mode": "debug"
  },
  "log": {
    "file": {
      "file_name": "/var/log/go-base-api.log",
      "max_size": 10,
      "max_backups": 10,
      "max_age": 10
    },
    "console_out_async": false,
    "level": "info"
  },
  "database": {
    "type": "mysql",
    "path": "api:password@tcp(mariadb:3306)/go-base?charset=utf8mb4\u0026parseTime=True\u0026loc=Local\u0026timeout=10s",
    "debug": false
  },
  "dash": {
    "jwt": "Fxar6KDjfp2NT8Uwa9Lgdf457OleFtyH",
    "address": "0.0.0.0:8800",
    "doc": false
  },
  "api": {
    "jwt": "wLMEO0geOXprXCp1odmSyBX4rGucjYdL",
    "address": "0.0.0.0:8899"
  },
  "cdn": {
    "access_key": "",
    "secret_key": "",
    "bucket": "",
    "dir": "",
    "domain": "",
    "host": ""
  },
  "wx_mini": {
    "app_id": "",
    "app_secret": "",
    "env": "develop"
  }
}